racetrack_job_wrapper/__init__.py
racetrack_job_wrapper/__main__.py
racetrack_job_wrapper/call.py
racetrack_job_wrapper/concurrency.py
racetrack_job_wrapper/docs.py
racetrack_job_wrapper/entrypoint.py
racetrack_job_wrapper/health.py
racetrack_job_wrapper/loader.py
racetrack_job_wrapper/main.py
racetrack_job_wrapper/metrics.py
racetrack_job_wrapper/py.typed
racetrack_job_wrapper/recordkeeper.py
racetrack_job_wrapper/response.py
racetrack_job_wrapper/server.py
racetrack_job_wrapper/standalone.py
racetrack_job_wrapper/template.py
racetrack_job_wrapper/validate.py
racetrack_job_wrapper/webview.py
racetrack_job_wrapper/wrapper.py
racetrack_job_wrapper/wrapper_api.py
racetrack_job_wrapper/api/__init__.py
racetrack_job_wrapper/api/debug.py
racetrack_job_wrapper/api/metrics.py
racetrack_job_wrapper/api/tracing.py
racetrack_job_wrapper/api/asgi/__init__.py
racetrack_job_wrapper/api/asgi/access_log.py
racetrack_job_wrapper/api/asgi/asgi_reloader.py
racetrack_job_wrapper/api/asgi/asgi_server.py
racetrack_job_wrapper/api/asgi/dispatcher.py
racetrack_job_wrapper/api/asgi/error_handler.py
racetrack_job_wrapper/api/asgi/fastapi.py
racetrack_job_wrapper/api/asgi/proxy.py
racetrack_job_wrapper/auth/__init__.py
racetrack_job_wrapper/auth/auth.py
racetrack_job_wrapper/auth/b64_token.py
racetrack_job_wrapper/auth/methods.py
racetrack_job_wrapper/auth/scope.py
racetrack_job_wrapper/client/__init__.py
racetrack_job_wrapper/client/env.py
racetrack_job_wrapper/log/__init__.py
racetrack_job_wrapper/log/context_error.py
racetrack_job_wrapper/log/errors.py
racetrack_job_wrapper/log/exception.py
racetrack_job_wrapper/log/logs.py
racetrack_job_wrapper/manifest/__init__.py
racetrack_job_wrapper/manifest/load.py
racetrack_job_wrapper/manifest/manifest.py
racetrack_job_wrapper/manifest/merge.py
racetrack_job_wrapper/utils/__init__.py
racetrack_job_wrapper/utils/auth.py
racetrack_job_wrapper/utils/datamodel.py
racetrack_job_wrapper/utils/env.py
racetrack_job_wrapper/utils/quantity.py
racetrack_job_runner-1.16.8.dist-info/LICENSE
racetrack_job_runner-1.16.8.dist-info/METADATA
racetrack_job_runner-1.16.8.dist-info/WHEEL
racetrack_job_runner-1.16.8.dist-info/entry_points.txt
racetrack_job_runner-1.16.8.dist-info/top_level.txt
racetrack_job_runner-1.16.8.dist-info/RECORD
