Metadata-Version: 2.1
Name: racetrack_job_runner
Version: 1.16.8
Summary: Racetrack Job Runner
Author-email: ERST <noreply@erst.dk>
License: Apache License 2.0
Project-URL: Homepage, https://github.com/TheRacetrack/job-runner-python-lib
Classifier: Programming Language :: Python :: 3
Classifier: Operating System :: OS Independent
Classifier: License :: OSI Approved :: Apache Software License
Requires-Python: >=3.8
License-File: LICENSE
Requires-Dist: PyYAML>=6.0.1
Requires-Dist: prometheus-client>=0.17.1
Requires-Dist: fastapi>=0.110.1
Requires-Dist: uvicorn[standard]>=0.29.0
Requires-Dist: python-multipart>=0.0.9
Requires-Dist: a2wsgi>=1.10.4
Requires-Dist: httpx>=0.24.0
Requires-Dist: Jinja2>=3.1.3
